stucklib/__init__.py
stucklib/packagelogic.py
stucklib-1.0.1.dist-info/METADATA
stucklib-1.0.1.dist-info/WHEEL
stucklib-1.0.1.dist-info/top_level.txt
stucklib-1.0.1.dist-info/RECORD
