Metadata-Version: 2.1
Name: stucklib
Version: 1.0.1
Summary: shhhhhhhhh
Author: Skib Skibidi
Author-email: your@email.com
License: MIT
